LICENSE.txt
MANIFEST.in
README.rst
setup.cfg
setup.py
versioneer.py
demos/general/demo_deep_cinac_training.py
demos/general/demo_deepcinac_evaluate_activity_classifier.py
demos/general/demo_deepcinac_predictions.py
demos/general/demo_deepcinac_simulated_movie_generator.py
demos/notebooks/deepcinac_simulated_movie_generator.ipynb
demos/notebooks/demo_deep_cinac_training.ipynb
demos/notebooks/demo_deepcinac_evaluate_activity_classifier.ipynb
demos/notebooks/demo_deepcinac_predictions.ipynb
src/deepcinac/__init__.py
src/deepcinac/__main__.py
src/deepcinac/_version.py
src/deepcinac/cell_type_categories_default.yaml
src/deepcinac/cinac_benchmarks.py
src/deepcinac/cinac_model.py
src/deepcinac/cinac_movie_patch.py
src/deepcinac/cinac_predictor.py
src/deepcinac/cinac_simulated_movie_generator.py
src/deepcinac/cinac_stratification.py
src/deepcinac/cinac_structures.py
src/deepcinac.egg-info/PKG-INFO
src/deepcinac.egg-info/SOURCES.txt
src/deepcinac.egg-info/dependency_links.txt
src/deepcinac.egg-info/entry_points.txt
src/deepcinac.egg-info/top_level.txt
src/deepcinac/gui/__init__.py
src/deepcinac/gui/cinac_gui.py
src/deepcinac/utils/__init__.py
src/deepcinac/utils/cells_map_utils.py
src/deepcinac/utils/cinac_file_utils.py
src/deepcinac/utils/display.py
src/deepcinac/utils/signal.py
src/deepcinac/utils/utils.py