Metadata-Version: 2.1
Name: deepcinac
Version: 1.1.8
Summary: A Calcium Imaging Toolbox for inferring neuronal activity
Home-page: https://gitlab.com/cossartlab/deepcinac
Author: Cossart Team
Author-email: julien.denis3@gmail.com
License: UNKNOWN
Project-URL: Bug Reports, https://gitlab.com/cossartlab/deepcinac/issues
Project-URL: Source, https://gitlab.com/cossartlab/deepcinac/tree/master/src
Keywords: CINAC deepCINAC deep-learning nwb neurodata-without-borders python toolbox calcium-imaging analysis
Platform: UNKNOWN
Classifier: Development Status :: 3 - Alpha
Classifier: Intended Audience :: Science/Research
Classifier: License :: OSI Approved :: MIT License
Classifier: Programming Language :: Python :: 3.6
Classifier: Programming Language :: Python :: 3.7
Requires-Python: >=3.5, <4
